{
  "id": 38838,
  "url": "https://gatherer.wizards.com/Pages/Card/Discussion.aspx?multiverseid=233237",
  "view_url": "https://web.archive.org/web/20201024211426/https://gatherer.wizards.com/Pages/Card/Discussion.aspx?multiverseid=233237",
  "posts": [
    {
      "id": "PopularPost268001",
      "post_content": "Why must you rotate?! You were in M10, 11, and 12 and suddenly you Mack your bags and leave standard? Your synergy with my double strike deck was unparalleled! I though we had something beautiful! Go ahead and more back in with your Modern. See if I care.   \n  \nPls come back.",
      "posted_by": "Doaj",
      "html": "<div class=\"post evenItem\" id=\"PopularPost268001\" style=\"background-color: rgba(255,255,255,0.08);\">\n<span class=\"postContent\" id=\"ctl00_ctl00_ctl00_MainContent_SubContent_SubContent_popularPosts_postsRepeater_ctl00_post\">Why must you rotate?! You were in M10, 11, and 12 and suddenly you Mack your bags and leave standard? Your synergy with my double strike deck was unparalleled! I though we had something beautiful! Go ahead and more back in with your Modern. See if I care. <br/><br/>Pls come back.</span>\n<div class=\"postDetails\" id=\"ctl00_ctl00_ctl00_MainContent_SubContent_SubContent_popularPosts_postsRepeater_ctl00_postDetails\" style=\"padding-top: 5px;\">\n<div class=\"reportAbuse\">\n<a href=\"../../Classes/Controls/#\" id=\"ctl00_ctl00_ctl00_MainContent_SubContent_SubContent_popularPosts_postsRepeater_ctl00_reportAbuseLink\" onclick=\"HandleReportPost(this, '268001'); return false;\">\r\n                                    Report Abuse</a>\u00a0\u00a0\r\n                                    \r\n                            </div>\n<div class=\"postedBy\">\r\n                                Posted By: \r\n                                <span id=\"PostedBy2929\">Doaj</span>\r\n                                (9/14/2012 4:45:03 AM)\r\n                            </div>\n<div class=\"postRating\">\n<div class=\"postRatingLabel\">\r\n                                    Rating:\u00a0\r\n                                </div>\n<div style=\"float: left;\">\n<div class=\"starRating\" id=\"ctl00_ctl00_ctl00_MainContent_SubContent_SubContent_popularPosts_postsRepeater_ctl00_postRating_starRating\"><img alt=\"0.5\" src=\"../../Images/Stars/LeftSolidSmall.png\"/><img alt=\"1.0\" src=\"../../Images/Stars/RightSolidSmall.png\"/><img alt=\"1.5\" src=\"../../Images/Stars/LeftSolidSmall.png\"/><img alt=\"2.0\" src=\"../../Images/Stars/RightSolidSmall.png\"/><img alt=\"2.5\" src=\"../../Images/Stars/LeftSolidSmall.png\"/><img alt=\"3.0\" src=\"../../Images/Stars/RightSolidSmall.png\"/><img alt=\"3.5\" src=\"../../Images/Stars/LeftSolidSmall.png\"/><img alt=\"4.0\" src=\"../../Images/Stars/RightSolidSmall.png\"/><img alt=\"4.5\" src=\"../../Images/Stars/LeftSolidSmall.png\"/><img alt=\"5.0\" src=\"../../Images/Stars/RightSolidSmall.png\"/>\n<br/>\n</div>\n</div>\n<br class=\"clear\"/>\n</div>\n<div class=\"postRating\">\n<div class=\"postRatingLabel\">\r\n                                    \u00a0\r\n                                </div>\n<div style=\"float: left;\">\n</div>\n<br class=\"clear\"/>\n</div>\n<br class=\"clear\"/>\n</div>\n</div>"
    },
    {
      "id": "PopularPost193239",
      "post_content": "This card is a lot better then [Crusade](/Pages/Card/Details.aspx?name=Crusade) due to it only affecting your creatures. The only time [Crusade](/Pages/Card/Details.aspx?name=Crusade) is better is 2HG. Also a permanent boost for only two Mana, well I would like four please 5/5.",
      "posted_by": "Dr_Fletchers",
      "html": "<div class=\"post oddItem\" id=\"PopularPost193239\">\n<span class=\"postContent\" id=\"ctl00_ctl00_ctl00_MainContent_SubContent_SubContent_popularPosts_postsRepeater_ctl01_post\">This card is a lot better then <a class=\"autoCard\" data:cardname=\"Crusade\" href=\"/Pages/Card/Details.aspx?name=Crusade\">Crusade</a> due to it only affecting your creatures. The only time <a class=\"autoCard\" data:cardname=\"Crusade\" href=\"/Pages/Card/Details.aspx?name=Crusade\">Crusade</a> is better is 2HG. Also a permanent boost for only two Mana, well I would like four please 5/5.</span>\n<div class=\"postDetails\" id=\"ctl00_ctl00_ctl00_MainContent_SubContent_SubContent_popularPosts_postsRepeater_ctl01_postDetails\" style=\"padding-top: 5px;\">\n<div class=\"reportAbuse\">\n<a href=\"http://wizards.custhelp.com/cgi-bin/wizards.cfg/php/enduser/ask.php?p_prods=522,706,739&amp;p_cats=\" id=\"ctl00_ctl00_ctl00_MainContent_SubContent_SubContent_popularPosts_postsRepeater_ctl01_reportAbuseLink\" onclick=\"HandleReportPost(this, '193239'); return false;\">\r\n                                    Report Abuse</a>\u00a0\u00a0\r\n                                \r\n                            </div>\n<div class=\"postedBy\">\r\n                                Posted By: \r\n                                <span id=\"PostedBy70509\">Dr_Fletchers</span>\r\n                                (9/3/2011 2:05:01 AM)\r\n                            </div>\n<div class=\"postRating\">\n<div class=\"postRatingLabel\">\r\n                                    Rating:\u00a0\r\n                                </div>\n<div style=\"float: left;\">\n<div class=\"starRating\" id=\"ctl00_ctl00_ctl00_MainContent_SubContent_SubContent_popularPosts_postsRepeater_ctl01_postRating_starRating\"><img alt=\"0.5\" src=\"../../Images/Stars/LeftSolidSmall.png\"/><img alt=\"1.0\" src=\"../../Images/Stars/RightSolidSmall.png\"/><img alt=\"1.5\" src=\"../../Images/Stars/LeftSolidSmall.png\"/><img alt=\"2.0\" src=\"../../Images/Stars/RightSolidSmall.png\"/><img alt=\"2.5\" src=\"../../Images/Stars/LeftSolidSmall.png\"/><img alt=\"3.0\" src=\"../../Images/Stars/RightSolidSmall.png\"/><img alt=\"3.5\" src=\"../../Images/Stars/LeftSolidSmall.png\"/><img alt=\"4.0\" src=\"../../Images/Stars/RightSolidSmall.png\"/><img alt=\"4.5\" src=\"../../Images/Stars/LeftSolidSmall.png\"/><img alt=\"5.0\" src=\"../../Images/Stars/RightSolidSmall.png\"/>\n<br/>\n</div>\n</div>\n<br class=\"clear\"/>\n</div>\n<div class=\"postRating\">\n<div class=\"postRatingLabel\">\r\n                                    \u00a0\r\n                                </div>\n<div style=\"float: left;\">\n</div>\n<br class=\"clear\"/>\n</div>\n</div>\n<br class=\"clear\"/>\n</div>"
    },
    {
      "id": "PopularPost331993",
      "post_content": "why do they all have shoulder-lasers",
      "posted_by": "NanakoAC",
      "html": "<div class=\"post evenItem\" id=\"PopularPost331993\" style=\"background-color: rgba(255,255,255,0.08);\">\n<span class=\"postContent\" id=\"ctl00_ctl00_ctl00_MainContent_SubContent_SubContent_popularPosts_postsRepeater_ctl02_post\">why do they all have shoulder-lasers</span>\n<div class=\"postDetails\" id=\"ctl00_ctl00_ctl00_MainContent_SubContent_SubContent_popularPosts_postsRepeater_ctl02_postDetails\" style=\"padding-top: 5px;\">\n<div class=\"reportAbuse\">\n<a href=\"../../Classes/Controls/#\" id=\"ctl00_ctl00_ctl00_MainContent_SubContent_SubContent_popularPosts_postsRepeater_ctl02_reportAbuseLink\" onclick=\"HandleReportPost(this, '331993'); return false;\">\r\n                                    Report Abuse</a>\u00a0\u00a0\r\n                                    \r\n                            </div>\n<div class=\"postedBy\">\r\n                                Posted By: \r\n                                <span id=\"PostedBy92916\">NanakoAC</span>\r\n                                (7/27/2013 1:11:36 PM)\r\n                            </div>\n<div class=\"postRating\">\n<div class=\"postRatingLabel\">\r\n                                    Rating:\u00a0\r\n                                </div>\n<div style=\"float: left;\">\n<div class=\"starRating\" id=\"ctl00_ctl00_ctl00_MainContent_SubContent_SubContent_popularPosts_postsRepeater_ctl02_postRating_starRating\"><img alt=\"0.5\" src=\"../../Images/Stars/LeftSolidSmall.png\"/><img alt=\"1.0\" src=\"../../Images/Stars/RightSolidSmall.png\"/><img alt=\"1.5\" src=\"../../Images/Stars/LeftSolidSmall.png\"/><img alt=\"2.0\" src=\"../../Images/Stars/RightSolidSmall.png\"/><img alt=\"2.5\" src=\"../../Images/Stars/LeftSolidSmall.png\"/><img alt=\"3.0\" src=\"../../Images/Stars/RightSolidSmall.png\"/><img alt=\"3.5\" src=\"../../Images/Stars/LeftSolidSmall.png\"/><img alt=\"4.0\" src=\"../../Images/Stars/RightSolidSmall.png\"/><img alt=\"4.5\" src=\"../../Images/Stars/LeftSolidSmall.png\"/><img alt=\"5.0\" src=\"../../Images/Stars/RightSolidSmall.png\"/>\n<br/>\n</div>\n</div>\n<br class=\"clear\"/>\n</div>\n<div class=\"postRating\">\n<div class=\"postRatingLabel\">\r\n                                    \u00a0\r\n                                </div>\n<div style=\"float: left;\">\n</div>\n<br class=\"clear\"/>\n</div>\n<br class=\"clear\"/>\n</div>\n</div>"
    },
    {
      "id": "PopularPost187652",
      "post_content": "A sweet card, with low cost, great effect, and possibly one of the best magic illustrations I've seen. ",
      "posted_by": "deadeye1387",
      "html": "<div class=\"post oddItem\" id=\"PopularPost187652\">\n<span class=\"postContent\" id=\"ctl00_ctl00_ctl00_MainContent_SubContent_SubContent_popularPosts_postsRepeater_ctl03_post\">A sweet card, with low cost, great effect, and possibly one of the best magic illustrations I've seen. </span>\n<div class=\"postDetails\" id=\"ctl00_ctl00_ctl00_MainContent_SubContent_SubContent_popularPosts_postsRepeater_ctl03_postDetails\" style=\"padding-top: 5px;\">\n<div class=\"reportAbuse\">\n<a href=\"http://wizards.custhelp.com/cgi-bin/wizards.cfg/php/enduser/ask.php?p_prods=522,706,739&amp;p_cats=\" id=\"ctl00_ctl00_ctl00_MainContent_SubContent_SubContent_popularPosts_postsRepeater_ctl03_reportAbuseLink\" onclick=\"HandleReportPost(this, '187652'); return false;\">\r\n                                    Report Abuse</a>\u00a0\u00a0\r\n                                \r\n                            </div>\n<div class=\"postedBy\">\r\n                                Posted By: \r\n                                <span id=\"PostedBy68882\">deadeye1387</span>\r\n                                (8/13/2011 3:49:23 PM)\r\n                            </div>\n<div class=\"postRating\">\n<div class=\"postRatingLabel\">\r\n                                    Rating:\u00a0\r\n                                </div>\n<div style=\"float: left;\">\n<div class=\"starRating\" id=\"ctl00_ctl00_ctl00_MainContent_SubContent_SubContent_popularPosts_postsRepeater_ctl03_postRating_starRating\"><img alt=\"0.5\" src=\"../../Images/Stars/LeftSolidSmall.png\"/><img alt=\"1.0\" src=\"../../Images/Stars/RightSolidSmall.png\"/><img alt=\"1.5\" src=\"../../Images/Stars/LeftSolidSmall.png\"/><img alt=\"2.0\" src=\"../../Images/Stars/RightSolidSmall.png\"/><img alt=\"2.5\" src=\"../../Images/Stars/LeftSolidSmall.png\"/><img alt=\"3.0\" src=\"../../Images/Stars/RightSolidSmall.png\"/><img alt=\"3.5\" src=\"../../Images/Stars/LeftSolidSmall.png\"/><img alt=\"4.0\" src=\"../../Images/Stars/RightSolidSmall.png\"/><img alt=\"4.5\" src=\"../../Images/Stars/LeftSolidSmall.png\"/><img alt=\"5.0\" src=\"../../Images/Stars/RightClearSmall.png\"/>\n<br/>\n</div>\n</div>\n<br class=\"clear\"/>\n</div>\n<div class=\"postRating\">\n<div class=\"postRatingLabel\">\r\n                                    \u00a0\r\n                                </div>\n<div style=\"float: left;\">\n</div>\n<br class=\"clear\"/>\n</div>\n</div>\n<br class=\"clear\"/>\n</div>"
    },
    {
      "id": "PopularPost201950",
      "post_content": "With the new humans in Innistrad, this card's a pretty nice boost when you're swarming with your humans (if you're playing mono-white).  \nJust be careful, the +1/+1 can make your creatures out of reach for [Mentor of the Meek](/Pages/Card/Details.aspx?name=Mentor of the Meek)'s ability.",
      "posted_by": "infernox10",
      "html": "<div class=\"post evenItem\" id=\"PopularPost201950\" style=\"background-color: rgba(255,255,255,0.08);\">\n<span class=\"postContent\" id=\"ctl00_ctl00_ctl00_MainContent_SubContent_SubContent_popularPosts_postsRepeater_ctl04_post\">With the new humans in Innistrad, this card's a pretty nice boost when you're swarming with your humans (if you're playing mono-white).<br/>Just be careful, the +1/+1 can make your creatures out of reach for <a class=\"autoCard\" data:cardname=\"Mentor of the Meek\" href=\"/Pages/Card/Details.aspx?name=Mentor of the Meek\">Mentor of the Meek</a>'s ability.</span>\n<div class=\"postDetails\" id=\"ctl00_ctl00_ctl00_MainContent_SubContent_SubContent_popularPosts_postsRepeater_ctl04_postDetails\" style=\"padding-top: 5px;\">\n<div class=\"reportAbuse\">\n<a href=\"../../Classes/Controls/#\" id=\"ctl00_ctl00_ctl00_MainContent_SubContent_SubContent_popularPosts_postsRepeater_ctl04_reportAbuseLink\" onclick=\"HandleReportPost(this, '201950'); return false;\">\r\n                                    Report Abuse</a>\u00a0\u00a0\r\n                                    \r\n                            </div>\n<div class=\"postedBy\">\r\n                                Posted By: \r\n                                <span id=\"PostedBy35140\">infernox10</span>\r\n                                (10/10/2011 6:26:57 AM)\r\n                            </div>\n<div class=\"postRating\">\n<div class=\"postRatingLabel\">\r\n                                    Rating:\u00a0\r\n                                </div>\n<div style=\"float: left;\">\n<div class=\"starRating\" id=\"ctl00_ctl00_ctl00_MainContent_SubContent_SubContent_popularPosts_postsRepeater_ctl04_postRating_starRating\"><img alt=\"0.5\" src=\"../../Images/Stars/LeftSolidSmall.png\"/><img alt=\"1.0\" src=\"../../Images/Stars/RightSolidSmall.png\"/><img alt=\"1.5\" src=\"../../Images/Stars/LeftSolidSmall.png\"/><img alt=\"2.0\" src=\"../../Images/Stars/RightSolidSmall.png\"/><img alt=\"2.5\" src=\"../../Images/Stars/LeftSolidSmall.png\"/><img alt=\"3.0\" src=\"../../Images/Stars/RightSolidSmall.png\"/><img alt=\"3.5\" src=\"../../Images/Stars/LeftSolidSmall.png\"/><img alt=\"4.0\" src=\"../../Images/Stars/RightSolidSmall.png\"/><img alt=\"4.5\" src=\"../../Images/Stars/LeftClearSmall.png\"/><img alt=\"5.0\" src=\"../../Images/Stars/RightClearSmall.png\"/>\n<br/>\n</div>\n</div>\n<br class=\"clear\"/>\n</div>\n<div class=\"postRating\">\n<div class=\"postRatingLabel\">\r\n                                    \u00a0\r\n                                </div>\n<div style=\"float: left;\">\n</div>\n<br class=\"clear\"/>\n</div>\n<br class=\"clear\"/>\n</div>\n</div>"
    },
    {
      "id": "PopularPost219402",
      "post_content": "just to reiterate what infernox10 said, this can screw over cards like [Mentor of the Meek](/Pages/Card/Details.aspx?name=Mentor of the Meek).  \n  \n9/22/2011 Apply power bonuses from counters the creature enters the battlefield with and continuous effects like [Mayor of Avabruck](/Pages/Card/Details.aspx?name=Mayor of Avabruck)'s when checking to see if Mentor of the Meek's ability will trigger.",
      "posted_by": "raptorman333",
      "html": "<div class=\"post oddItem\" id=\"PopularPost219402\">\n<span class=\"postContent\" id=\"ctl00_ctl00_ctl00_MainContent_SubContent_SubContent_popularPosts_postsRepeater_ctl05_post\">just to reiterate what  infernox10 said, this can screw over cards like  <a class=\"autoCard\" data:cardname=\"Mentor of the Meek\" href=\"/Pages/Card/Details.aspx?name=Mentor of the Meek\">Mentor of the Meek</a>.<br/><br/>9/22/2011 \tApply power bonuses from counters the creature enters the battlefield with and continuous effects like <a class=\"autoCard\" data:cardname=\"Mayor of Avabruck\" href=\"/Pages/Card/Details.aspx?name=Mayor of Avabruck\">Mayor of Avabruck</a>'s when checking to see if Mentor of the Meek's ability will trigger.</span>\n<div class=\"postDetails\" id=\"ctl00_ctl00_ctl00_MainContent_SubContent_SubContent_popularPosts_postsRepeater_ctl05_postDetails\" style=\"padding-top: 5px;\">\n<div class=\"reportAbuse\">\n<a href=\"http://wizards.custhelp.com/cgi-bin/wizards.cfg/php/enduser/ask.php?p_prods=522,706,739&amp;p_cats=\" id=\"ctl00_ctl00_ctl00_MainContent_SubContent_SubContent_popularPosts_postsRepeater_ctl05_reportAbuseLink\" onclick=\"HandleReportPost(this, '219402'); return false;\">\r\n                                    Report Abuse</a>\u00a0\u00a0\r\n                                \r\n                            </div>\n<div class=\"postedBy\">\r\n                                Posted By: \r\n                                <span id=\"PostedBy17597\">raptorman333</span>\r\n                                (1/9/2012 11:30:49 AM)\r\n                            </div>\n<div class=\"postRating\">\n<div class=\"postRatingLabel\">\r\n                                    Rating:\u00a0\r\n                                </div>\n<div style=\"float: left;\">\n<div class=\"starRating\" id=\"ctl00_ctl00_ctl00_MainContent_SubContent_SubContent_popularPosts_postsRepeater_ctl05_postRating_starRating\"><img alt=\"0.5\" src=\"../../Images/Stars/LeftSolidSmall.png\"/><img alt=\"1.0\" src=\"../../Images/Stars/RightSolidSmall.png\"/><img alt=\"1.5\" src=\"../../Images/Stars/LeftSolidSmall.png\"/><img alt=\"2.0\" src=\"../../Images/Stars/RightSolidSmall.png\"/><img alt=\"2.5\" src=\"../../Images/Stars/LeftSolidSmall.png\"/><img alt=\"3.0\" src=\"../../Images/Stars/RightSolidSmall.png\"/><img alt=\"3.5\" src=\"../../Images/Stars/LeftSolidSmall.png\"/><img alt=\"4.0\" src=\"../../Images/Stars/RightClearSmall.png\"/><img alt=\"4.5\" src=\"../../Images/Stars/LeftClearSmall.png\"/><img alt=\"5.0\" src=\"../../Images/Stars/RightClearSmall.png\"/>\n<br/>\n</div>\n</div>\n<br class=\"clear\"/>\n</div>\n<div class=\"postRating\">\n<div class=\"postRatingLabel\">\r\n                                    \u00a0\r\n                                </div>\n<div style=\"float: left;\">\n</div>\n<br class=\"clear\"/>\n</div>\n</div>\n<br class=\"clear\"/>\n</div>"
    },
    {
      "id": "PopularPost177214",
      "post_content": "good to see a reprint that helps my soldier/angel deck to stay in standard not the best but well worth the two mana",
      "posted_by": "Tantudo",
      "html": "<div class=\"post evenItem\" id=\"PopularPost177214\" style=\"background-color: rgba(255,255,255,0.08);\">\n<span class=\"postContent\" id=\"ctl00_ctl00_ctl00_MainContent_SubContent_SubContent_popularPosts_postsRepeater_ctl06_post\">good to see a reprint that helps my soldier/angel deck to stay in standard not the best but well worth the two mana</span>\n<div class=\"postDetails\" id=\"ctl00_ctl00_ctl00_MainContent_SubContent_SubContent_popularPosts_postsRepeater_ctl06_postDetails\" style=\"padding-top: 5px;\">\n<div class=\"reportAbuse\">\n<a href=\"../../Classes/Controls/#\" id=\"ctl00_ctl00_ctl00_MainContent_SubContent_SubContent_popularPosts_postsRepeater_ctl06_reportAbuseLink\" onclick=\"HandleReportPost(this, '177214'); return false;\">\r\n                                    Report Abuse</a>\u00a0\u00a0\r\n                                    \r\n                            </div>\n<div class=\"postedBy\">\r\n                                Posted By: \r\n                                <span id=\"PostedBy65850\">Tantudo</span>\r\n                                (7/9/2011 11:39:17 PM)\r\n                            </div>\n<div class=\"postRating\">\n<div class=\"postRatingLabel\">\r\n                                    Rating:\u00a0\r\n                                </div>\n<div style=\"float: left;\">\n<div class=\"starRating\" id=\"ctl00_ctl00_ctl00_MainContent_SubContent_SubContent_popularPosts_postsRepeater_ctl06_postRating_starRating\"><img alt=\"0.5\" src=\"../../Images/Stars/LeftSolidSmall.png\"/><img alt=\"1.0\" src=\"../../Images/Stars/RightSolidSmall.png\"/><img alt=\"1.5\" src=\"../../Images/Stars/LeftSolidSmall.png\"/><img alt=\"2.0\" src=\"../../Images/Stars/RightSolidSmall.png\"/><img alt=\"2.5\" src=\"../../Images/Stars/LeftSolidSmall.png\"/><img alt=\"3.0\" src=\"../../Images/Stars/RightSolidSmall.png\"/><img alt=\"3.5\" src=\"../../Images/Stars/LeftSolidSmall.png\"/><img alt=\"4.0\" src=\"../../Images/Stars/RightClearSmall.png\"/><img alt=\"4.5\" src=\"../../Images/Stars/LeftClearSmall.png\"/><img alt=\"5.0\" src=\"../../Images/Stars/RightClearSmall.png\"/>\n<br/>\n</div>\n</div>\n<br class=\"clear\"/>\n</div>\n<div class=\"postRating\">\n<div class=\"postRatingLabel\">\r\n                                    \u00a0\r\n                                </div>\n<div style=\"float: left;\">\n</div>\n<br class=\"clear\"/>\n</div>\n<br class=\"clear\"/>\n</div>\n</div>"
    },
    {
      "id": "PopularPost236847",
      "post_content": "Combos with white",
      "posted_by": "Trehy4",
      "html": "<div class=\"post oddItem\" id=\"PopularPost236847\">\n<span class=\"postContent\" id=\"ctl00_ctl00_ctl00_MainContent_SubContent_SubContent_popularPosts_postsRepeater_ctl07_post\">Combos with white</span>\n<div class=\"postDetails\" id=\"ctl00_ctl00_ctl00_MainContent_SubContent_SubContent_popularPosts_postsRepeater_ctl07_postDetails\" style=\"padding-top: 5px;\">\n<div class=\"reportAbuse\">\n<a href=\"http://wizards.custhelp.com/cgi-bin/wizards.cfg/php/enduser/ask.php?p_prods=522,706,739&amp;p_cats=\" id=\"ctl00_ctl00_ctl00_MainContent_SubContent_SubContent_popularPosts_postsRepeater_ctl07_reportAbuseLink\" onclick=\"HandleReportPost(this, '236847'); return false;\">\r\n                                    Report Abuse</a>\u00a0\u00a0\r\n                                \r\n                            </div>\n<div class=\"postedBy\">\r\n                                Posted By: \r\n                                <span id=\"PostedBy79957\">Trehy4</span>\r\n                                (4/9/2012 4:08:04 PM)\r\n                            </div>\n<div class=\"postRating\">\n<div class=\"postRatingLabel\">\r\n                                    Rating:\u00a0\r\n                                </div>\n<div style=\"float: left;\">\n<div class=\"starRating\" id=\"ctl00_ctl00_ctl00_MainContent_SubContent_SubContent_popularPosts_postsRepeater_ctl07_postRating_starRating\"><img alt=\"0.5\" src=\"../../Images/Stars/LeftSolidSmall.png\"/><img alt=\"1.0\" src=\"../../Images/Stars/RightSolidSmall.png\"/><img alt=\"1.5\" src=\"../../Images/Stars/LeftSolidSmall.png\"/><img alt=\"2.0\" src=\"../../Images/Stars/RightSolidSmall.png\"/><img alt=\"2.5\" src=\"../../Images/Stars/LeftSolidSmall.png\"/><img alt=\"3.0\" src=\"../../Images/Stars/RightSolidSmall.png\"/><img alt=\"3.5\" src=\"../../Images/Stars/LeftClearSmall.png\"/><img alt=\"4.0\" src=\"../../Images/Stars/RightClearSmall.png\"/><img alt=\"4.5\" src=\"../../Images/Stars/LeftClearSmall.png\"/><img alt=\"5.0\" src=\"../../Images/Stars/RightClearSmall.png\"/>\n<br/>\n</div>\n</div>\n<br class=\"clear\"/>\n</div>\n<div class=\"postRating\">\n<div class=\"postRatingLabel\">\r\n                                    \u00a0\r\n                                </div>\n<div style=\"float: left;\">\n</div>\n<br class=\"clear\"/>\n</div>\n</div>\n<br class=\"clear\"/>\n</div>"
    },
    {
      "id": "PopularPost190277",
      "post_content": "This card was unnecessary. What was wrong with [Glorious Anthem](/Pages/Card/Details.aspx?name=Glorious Anthem ) ?",
      "posted_by": "sincleanser",
      "html": "<div class=\"post evenItem\" id=\"PopularPost190277\" style=\"background-color: rgba(255,255,255,0.08);\">\n<span class=\"postContent\" id=\"ctl00_ctl00_ctl00_MainContent_SubContent_SubContent_popularPosts_postsRepeater_ctl08_post\">This card was unnecessary.  What was wrong with \t<a class=\"autoCard\" data:cardname=\"Glorious Anthem \" href=\"/Pages/Card/Details.aspx?name=Glorious Anthem \">Glorious Anthem </a>?</span>\n<div class=\"postDetails\" id=\"ctl00_ctl00_ctl00_MainContent_SubContent_SubContent_popularPosts_postsRepeater_ctl08_postDetails\" style=\"padding-top: 5px;\">\n<div class=\"reportAbuse\">\n<a href=\"../../Classes/Controls/#\" id=\"ctl00_ctl00_ctl00_MainContent_SubContent_SubContent_popularPosts_postsRepeater_ctl08_reportAbuseLink\" onclick=\"HandleReportPost(this, '190277'); return false;\">\r\n                                    Report Abuse</a>\u00a0\u00a0\r\n                                    \r\n                            </div>\n<div class=\"postedBy\">\r\n                                Posted By: \r\n                                <span id=\"PostedBy68260\">sincleanser</span>\r\n                                (8/23/2011 8:59:25 AM)\r\n                            </div>\n<div class=\"postRating\">\n<div class=\"postRatingLabel\">\r\n                                    Rating:\u00a0\r\n                                </div>\n<div style=\"float: left;\">\n<div class=\"starRating\" id=\"ctl00_ctl00_ctl00_MainContent_SubContent_SubContent_popularPosts_postsRepeater_ctl08_postRating_starRating\"><img alt=\"0.5\" src=\"../../Images/Stars/LeftSolidSmall.png\"/><img alt=\"1.0\" src=\"../../Images/Stars/RightSolidSmall.png\"/><img alt=\"1.5\" src=\"../../Images/Stars/LeftSolidSmall.png\"/><img alt=\"2.0\" src=\"../../Images/Stars/RightSolidSmall.png\"/><img alt=\"2.5\" src=\"../../Images/Stars/LeftClearSmall.png\"/><img alt=\"3.0\" src=\"../../Images/Stars/RightClearSmall.png\"/><img alt=\"3.5\" src=\"../../Images/Stars/LeftClearSmall.png\"/><img alt=\"4.0\" src=\"../../Images/Stars/RightClearSmall.png\"/><img alt=\"4.5\" src=\"../../Images/Stars/LeftClearSmall.png\"/><img alt=\"5.0\" src=\"../../Images/Stars/RightClearSmall.png\"/>\n<br/>\n</div>\n</div>\n<br class=\"clear\"/>\n</div>\n<div class=\"postRating\">\n<div class=\"postRatingLabel\">\r\n                                    \u00a0\r\n                                </div>\n<div style=\"float: left;\">\n</div>\n<br class=\"clear\"/>\n</div>\n<br class=\"clear\"/>\n</div>\n</div>"
    },
    {
      "id": "PopularPost192217",
      "post_content": "Love this card. I use this and [Guardian's Pledge](/Pages/Card/Details.aspx?name=Guardian's Pledge) to provide some extra oomph to my white aggro deck. Check it out:  \n  \nhttp://birdsofparadise-mtg.blogspot.com/2011/08/honor-pledge.html  ",
      "posted_by": "badmalloc",
      "html": "<div class=\"post oddItem\" id=\"PopularPost192217\">\n<span class=\"postContent\" id=\"ctl00_ctl00_ctl00_MainContent_SubContent_SubContent_popularPosts_postsRepeater_ctl09_post\">Love this card. I use this and <a class=\"autoCard\" data:cardname=\"Guardian's Pledge\" href=\"/Pages/Card/Details.aspx?name=Guardian's Pledge\">Guardian's Pledge</a> to provide some extra oomph to my white aggro deck. Check it out:<br/><br/>http://birdsofparadise-mtg.blogspot.com/2011/08/honor-pledge.html<br/></span>\n<div class=\"postDetails\" id=\"ctl00_ctl00_ctl00_MainContent_SubContent_SubContent_popularPosts_postsRepeater_ctl09_postDetails\" style=\"padding-top: 5px;\">\n<div class=\"reportAbuse\">\n<a href=\"http://wizards.custhelp.com/cgi-bin/wizards.cfg/php/enduser/ask.php?p_prods=522,706,739&amp;p_cats=\" id=\"ctl00_ctl00_ctl00_MainContent_SubContent_SubContent_popularPosts_postsRepeater_ctl09_reportAbuseLink\" onclick=\"HandleReportPost(this, '192217'); return false;\">\r\n                                    Report Abuse</a>\u00a0\u00a0\r\n                                \r\n                            </div>\n<div class=\"postedBy\">\r\n                                Posted By: \r\n                                <span id=\"PostedBy36122\">badmalloc</span>\r\n                                (8/29/2011 9:49:50 PM)\r\n                            </div>\n<div class=\"postRating\">\n<div class=\"postRatingLabel\">\r\n                                    Rating:\u00a0\r\n                                </div>\n<div style=\"float: left;\">\n<div class=\"starRating\" id=\"ctl00_ctl00_ctl00_MainContent_SubContent_SubContent_popularPosts_postsRepeater_ctl09_postRating_starRating\"><img alt=\"0.5\" src=\"../../Images/Stars/LeftSolidSmall.png\"/><img alt=\"1.0\" src=\"../../Images/Stars/RightSolidSmall.png\"/><img alt=\"1.5\" src=\"../../Images/Stars/LeftSolidSmall.png\"/><img alt=\"2.0\" src=\"../../Images/Stars/RightSolidSmall.png\"/><img alt=\"2.5\" src=\"../../Images/Stars/LeftClearSmall.png\"/><img alt=\"3.0\" src=\"../../Images/Stars/RightClearSmall.png\"/><img alt=\"3.5\" src=\"../../Images/Stars/LeftClearSmall.png\"/><img alt=\"4.0\" src=\"../../Images/Stars/RightClearSmall.png\"/><img alt=\"4.5\" src=\"../../Images/Stars/LeftClearSmall.png\"/><img alt=\"5.0\" src=\"../../Images/Stars/RightClearSmall.png\"/>\n<br/>\n</div>\n</div>\n<br class=\"clear\"/>\n</div>\n<div class=\"postRating\">\n<div class=\"postRatingLabel\">\r\n                                    \u00a0\r\n                                </div>\n<div style=\"float: left;\">\n</div>\n<br class=\"clear\"/>\n</div>\n</div>\n<br class=\"clear\"/>\n</div>"
    }
  ]
}